node.ext.fs-1.1-py3.9-nspkg.pth
node/ext/fs/__init__.py
node/ext/fs/directory.py
node/ext/fs/file.py
node/ext/fs/interfaces.py
node/ext/fs/location.py
node/ext/fs/mode.py
node/ext/fs/tests.py
node.ext.fs-1.1.dist-info/LICENSE.rst
node.ext.fs-1.1.dist-info/METADATA
node.ext.fs-1.1.dist-info/WHEEL
node.ext.fs-1.1.dist-info/namespace_packages.txt
node.ext.fs-1.1.dist-info/top_level.txt
node.ext.fs-1.1.dist-info/zip-safe
node.ext.fs-1.1.dist-info/RECORD
