Metadata-Version: 2.1
Name: node.ext.fs
Version: 1.1
Summary: Filesystem abstraction based on nodes
Home-page: http://github.com/conestack/node.ext.fs
Author: Node Contributors
Author-email: dev@conestack.org
License: Simplified BSD
Keywords: node file system
Platform: UNKNOWN
Classifier: Development Status :: 5 - Production/Stable
Classifier: License :: OSI Approved :: BSD License
Classifier: Intended Audience :: Developers
Classifier: Topic :: Software Development
Classifier: Programming Language :: Python
Classifier: Programming Language :: Python :: 2.7
Classifier: Programming Language :: Python :: 3.7
Classifier: Programming Language :: Python :: 3.8
Classifier: Programming Language :: Python :: 3.9
Classifier: Programming Language :: Python :: 3.10
Requires-Dist: node (>=1.0)
Requires-Dist: setuptools
Provides-Extra: test
Requires-Dist: coverage ; extra == 'test'
